odoo/addons/helpdesk_mgmt_fieldservice/README.rst
odoo/addons/helpdesk_mgmt_fieldservice/__init__.py
odoo/addons/helpdesk_mgmt_fieldservice/__manifest__.py
odoo/addons/helpdesk_mgmt_fieldservice/i18n/ca.po
odoo/addons/helpdesk_mgmt_fieldservice/i18n/es.po
odoo/addons/helpdesk_mgmt_fieldservice/i18n/es_AR.po
odoo/addons/helpdesk_mgmt_fieldservice/i18n/fr.po
odoo/addons/helpdesk_mgmt_fieldservice/i18n/helpdesk_mgmt_fieldservice.pot
odoo/addons/helpdesk_mgmt_fieldservice/i18n/it.po
odoo/addons/helpdesk_mgmt_fieldservice/i18n/pt_BR.po
odoo/addons/helpdesk_mgmt_fieldservice/models/__init__.py
odoo/addons/helpdesk_mgmt_fieldservice/models/fsm_location.py
odoo/addons/helpdesk_mgmt_fieldservice/models/fsm_order.py
odoo/addons/helpdesk_mgmt_fieldservice/models/helpdesk_ticket.py
odoo/addons/helpdesk_mgmt_fieldservice/readme/CONFIGURE.md
odoo/addons/helpdesk_mgmt_fieldservice/readme/CONTRIBUTORS.md
odoo/addons/helpdesk_mgmt_fieldservice/readme/DESCRIPTION.md
odoo/addons/helpdesk_mgmt_fieldservice/readme/HISTORY.md
odoo/addons/helpdesk_mgmt_fieldservice/readme/INSTALL.md
odoo/addons/helpdesk_mgmt_fieldservice/readme/ROADMAP.md
odoo/addons/helpdesk_mgmt_fieldservice/readme/USAGE.md
odoo/addons/helpdesk_mgmt_fieldservice/security/ir.model.access.csv
odoo/addons/helpdesk_mgmt_fieldservice/static/description/icon.png
odoo/addons/helpdesk_mgmt_fieldservice/static/description/index.html
odoo/addons/helpdesk_mgmt_fieldservice/static/src/scss/helpdesk_column.scss
odoo/addons/helpdesk_mgmt_fieldservice/tests/__init__.py
odoo/addons/helpdesk_mgmt_fieldservice/tests/test_helpdesk_ticket_fsm_order.py
odoo/addons/helpdesk_mgmt_fieldservice/views/fsm_location_views.xml
odoo/addons/helpdesk_mgmt_fieldservice/views/fsm_order_views.xml
odoo/addons/helpdesk_mgmt_fieldservice/views/helpdesk_ticket_views.xml
odoo/addons/helpdesk_mgmt_fieldservice/wizards/__init__.py
odoo/addons/helpdesk_mgmt_fieldservice/wizards/fsm_order_close_wizard.py
odoo_addon_helpdesk_mgmt_fieldservice-18.0.1.1.2.dist-info/METADATA
odoo_addon_helpdesk_mgmt_fieldservice-18.0.1.1.2.dist-info/WHEEL
odoo_addon_helpdesk_mgmt_fieldservice-18.0.1.1.2.dist-info/top_level.txt
odoo_addon_helpdesk_mgmt_fieldservice-18.0.1.1.2.dist-info/RECORD
