Metadata-Version: 2.1
Name: odoo-addon-helpdesk_mgmt_fieldservice
Version: 18.0.1.1.2
Requires-Python: >=3.10
Requires-Dist: odoo-addon-fieldservice==18.0.*
Requires-Dist: odoo-addon-helpdesk_mgmt==18.0.*
Requires-Dist: odoo==18.0.*
Summary: Create service orders from a ticket
Home-page: https://github.com/OCA/helpdesk
License: AGPL-3
Author: Open Source Integrators, Escodoo, Odoo Community Association (OCA)
Author-email: support@odoo-community.org
Classifier: Programming Language :: Python
Classifier: Framework :: Odoo
Classifier: Framework :: Odoo :: 18.0
Classifier: License :: OSI Approved :: GNU Affero General Public License v3
